funcsubs/__init__.py
tests/__init__.py
tests/test_base.py
funcsubs-0.4.0.dist-info/LICENSE.txt
funcsubs-0.4.0.dist-info/METADATA
funcsubs-0.4.0.dist-info/WHEEL
funcsubs-0.4.0.dist-info/top_level.txt
funcsubs-0.4.0.dist-info/RECORD
