Metadata-Version: 2.1
Name: funcsubs
Version: 0.4.0
Summary: General function and method subscription system
Home-page: https://gitlab.com/SirEdvin/funcsubs
Author: Bogdan Gladyshev
Author-email: siredvin.dark@gmail.com
License: MIT license
Keywords: subscribtion event
Platform: UNKNOWN
Classifier: Development Status :: 5 - Production/Stable
Classifier: Intended Audience :: Developers
Classifier: License :: OSI Approved :: MIT License
Classifier: Natural Language :: English
Classifier: Programming Language :: Python :: 3.6
Classifier: Programming Language :: Python :: 3.7
Requires-Dist: frozendict (>=1.2)
